punctuationstripper/__init__.py
punctuationstripper/punctuation_stripper.py
punctuationstripper/tests.py
punctuationstripper-0.0.1.dist-info/LICENSE
punctuationstripper-0.0.1.dist-info/METADATA
punctuationstripper-0.0.1.dist-info/WHEEL
punctuationstripper-0.0.1.dist-info/top_level.txt
punctuationstripper-0.0.1.dist-info/RECORD
