Metadata-Version: 2.1
Name: punctuationstripper
Version: 0.0.1
Summary: A package to strip punctuation from text via a file or a basic string.
Home-page: https://github.com/TheDataDave/punctuationstripper
Author: David Flanders
Author-email: thedatadave@gmail.com
Keywords: python,punctuation,text cleaning,data cleaning,NLP,string manipulation
Classifier: Programming Language :: Python :: 3
Classifier: License :: OSI Approved :: MIT License
Classifier: Topic :: Software Development :: Libraries :: Python Modules
Classifier: Operating System :: OS Independent
License-File: LICENSE
